Workbook

Sheet Summary
A1: Family Court Metric Catalog — Missouri Pilot
A2: SUMMARY · 3-YEAR BUDGET BY CATEGORY
A4: Category | B4: Year 1 | C4: Year 2 | D4: Year 3 | E4: Total (3yr) | F4: % of Total
A5: Personnel | B5: =Detail!C22 -> 318000 | C5: =Detail!D22 -> 331000 | D5: =Detail!E22 -> 345000 | E5: =SUM(B5:D5) -> 994000 | F5: =E5/$E$11 -> 0.68339166
A6: Board & Reviews | B6: =Detail!C23 -> 42000 | C6: =Detail!D23 -> 44000 | D6: =Detail!E23 -> 46000 | E6: =SUM(B6:D6) -> 132000 | F6: =E6/$E$11 -> 0.090752212
A7: Infrastructure & Ops | B7: =Detail!C24 -> 46500 | C7: =Detail!D24 -> 48200 | D7: =Detail!E24 -> 50000 | E7: =SUM(B7:D7) -> 144700 | F7: =E7/$E$11 -> 0.099483675
A8: Academic Partnerships | B8: =Detail!C25 -> 45000 | C8: =Detail!D25 -> 45000 | D8: =Detail!E25 -> 45000 | E8: =SUM(B8:D8) -> 135000 | F8: =E8/$E$11 -> 0.092814762
A9: Contingency | B9: =Detail!C26 -> 15810 | C9: =Detail!D26 -> 14970 | D9: =Detail!E26 -> 18030 | E9: =SUM(B9:D9) -> 48810 | F9: =E9/$E$11 -> 0.033557693
A11: TOTAL | B11: =SUM(B5:B9) -> 467310 | C11: =SUM(C5:C9) -> 483170 | D11: =SUM(D5:D9) -> 504030 | E11: =SUM(E5:E9) -> 1454510 | F11: =E11/E11 -> 1
A14: Budget Integrity
A15: All Year 1/2/3 amounts pull directly from Detail sheet. Change a rate or FTE in Detail; all totals update automatically.

Sheet Detail
A1: Family Court Metric Catalog — Missouri Pilot
A2: DETAIL · LINE ITEMS (3-YEAR BUDGET)
A4: Line Item | B4: FTE / Units | C4: Year 1 | D4: Year 2 | E4: Year 3 | F4: Total (3yr) | G4: Source / Notes
A5: Executive Director | B5: 1.0 FTE | C5: 130000 | D5: 135000 | E5: 141000 | F5: =SUM(C5:E5) -> 406000 | G5: Nonprofit ED, STL market rate
A6: Engineering Lead (Founder) | B6: 1.0 FTE | C6: 95000 | D6: 99000 | E6: 103000 | F6: =SUM(C6:E6) -> 297000 | G6: Below-market founder salary
A7: Methodology Coordinator | B7: 0.5 FTE | C7: 43000 | D7: 45000 | E7: 47000 | F7: =SUM(C7:E7) -> 135000 | G7: Part-time research-ops role
A8: Research / Data Analyst | B8: 0.5 FTE | C8: 35000 | D8: 37000 | E8: 39000 | F8: =SUM(C8:E8) -> 111000 | G8: Part-time analytics role
A9: Contract — Privacy Audit | B9: 0.2 FTE | C9: 15000 | D9: 15000 | E9: 15000 | F9: =SUM(C9:E9) -> 45000 | G9: External auditor, annual engagement
A10: Methodology Board Honoraria | B10: 11 × 4 | C10: 22000 | D10: 22000 | E10: 22000 | F10: =SUM(C10:E10) -> 66000 | G10: 11 members × 4 meetings × $500
A11: Data Ethics Review Honoraria | B11: 5 × 2 | C11: 20000 | D11: 22000 | E11: 24000 | F11: =SUM(C11:E11) -> 66000 | G11: 5 members × ~2 reviews × $2,000
A12: AWS Infrastructure | B12: — | C12: 15000 | D12: 16200 | E12: 17500 | F12: =SUM(C12:E12) -> 48700 | G12: DynamoDB, Lambda, API Gtwy, S3, SSM
A13: Third-Party Tools (observability, etc.) | B13: — | C13: 8500 | D13: 9000 | E13: 9500 | F13: =SUM(C13:E13) -> 27000 | G13: Datadog/Sentry/compliance tooling
A14: Independent Security Audit | B14: Annual | C14: 12000 | D14: 12000 | E14: 12000 | F14: =SUM(C14:E14) -> 36000 | G14: Required by MOU before Month 6
A15: Insurance (Cyber $2M, E&O) | B15: — | C15: 8000 | D15: 8000 | E15: 8000 | F15: =SUM(C15:E15) -> 24000 | G15: Required by MOU Article IX
A16: Office / Meeting Costs | B16: — | C16: 3000 | D16: 3000 | E16: 3000 | F16: =SUM(C16:E16) -> 9000 | G16: Quarterly Board meeting logistics
... A20: Contingency (10% of operating) | B20: — | C20: 15810 | D20: 14970 | E20: 18030 | F20: =SUM(C20:E20) -> 48810 | G20: Unallocated reserve, Board-released
A22: Subtotal — Personnel | C22: =SUM(C5,C6,C7,C8,C9) -> 318000 | D22: =SUM(D5,D6,D7,D8,D9) -> 331000 | E22: =SUM(E5,E6,E7,E8,E9) -> 345000 | F22: =SUM(C22:E22) -> 994000
A23: Subtotal — Board & Reviews | C23: =SUM(C10,C11) -> 42000 | D23: =SUM(D10,D11) -> 44000 | E23: =SUM(E10,E11) -> 46000 | F23: =SUM(C23:E23) -> 132000
A24: Subtotal — Infrastructure & Ops | C24: =SUM(C12,C13,C14,C15,C16) -> 46500 | D24: =SUM(D12,D13,D14,D15,D16) -> 48200 | E24: =SUM(E12,E13,E14,E15,E16) -> 50000 | F24: =SUM(C24:E24) -> 144700
A25: Subtotal — Academic Partnerships | C25: =SUM(C17,C18,C19) -> 45000 | D25: =SUM(D17,D18,D19) -> 45000 | E25: =SUM(E17,E18,E19) -> 45000 | F25: =SUM(C25:E25) -> 135000
A26: Subtotal — Contingency | C26: =SUM(C20) -> 15810 | D26: =SUM(D20) -> 14970 | E26: =SUM(E20) -> 18030 | F26: =SUM(C26:E26) -> 48810
A28: GRAND TOTAL (3-YEAR PILOT) | C28: =C22+C23+C24+C25+C26 -> 467310 | D28: =D22+D23+D24+D25+D26 -> 483170 | E28: =E22+E23+E24+E25+E26 -> 504030 | F28: =SUM(C28:E28) -> 1454510

Sheet Funding Sources
A1: Funding Sources · 20% Cap Enforced
A2: NO SINGLE FUNDER MAY EXCEED 20% OF TOTAL BUDGET
A4: Total Budget (from Summary) | B4: =Summary!E11 -> 1454510
A5: 20% Cap Threshold | B5: =B4*0.2 -> 290902
A7: Funder Category | B7: Target % | C7: Target $ | D7: Secured $ | E7: Status / Notes
A8: Philanthropy — Access-to-Justice Foundations | B8: 0.4 | C8: =B8*$B$4 -> 581804 | D8: 0 | E8: Active cultivation · multi-funder stack
A9: Academic Institutional Partnerships | B9: 0.15 | C9: =B9*$B$4 -> 218176.5 | D9: 0 | E9: Contracted at partner level (Wash U, Mizzou, MO State)
A10: Individual & Community Donors | B10: 0.15 | C10: =B10*$B$4 -> 218176.5 | D10: 0 | E10: Ongoing direct fundraising
A11: CoTrackPro Subscription Revenue | B11: 0.1 | C11: =B11*$B$4 -> 145451 | D11: 0 | E11: Existing modest revenue stream
A12: Deferred — State Appropriation (post-pilot) | B12: 0.2 | C12: =B12*$B$4 -> 290902 | D12: 0 | E12: Not Phase 1; placeholder pending legislative action
A14: TOTAL | B14: =SUM(B8:B12) -> 1 | C14: =SUM(C8:C12) -> 1454510 | D14: =SUM(D8:D12) -> 0
A17: Cap Check — Any Funder Over 20%?
A18: Max single funder target % | B18: =MAX(B8:B12) -> 0.4
A19: Cap violation? | B19: =IF(B18>0.2,"YES — REBALANCE","OK") -> YES — REBALANCE

Sheet Assumptions
A1: Budget Assumptions
A2: DOCUMENT ANY CHANGE; SOURCE EVERY ASSUMPTION
A4: # | B4: Assumption | C4: Rationale | D4: Source / Reference
A5: 1 | B5: One executive director hired within 90 days of funding secured | C5: Operational leadership is the critical path for Phase 1 | D5: Standard nonprofit startup timeline
A6: 2 | B6: No staff growth beyond Year 1 headcount | C6: Keeps budget predictable; absorbs growth via contractors only | D6: Internal planning decision
A7: 3 | B7: Pilot circuits require no reimbursement | C7: MOU structure assumes voluntary participation | D7: OSCA Data-Sharing MOU (Doc 06), Article VIII
A8: 4 | B8: AWS costs stay within Activate credits for first 6 months | C8: New nonprofit qualifies for AWS Activate $5K tier | D8: AWS Activate program eligibility
A9: 5 | B9: Academic partners provide in-kind contribution (faculty time, IRB) | C9: Contracted $15k/yr supplements ~3-5x that value in-kind | D9: Standard academic partnership pattern
A10: 6 | B10: No litigation expenses in baseline budget | C10: Test cases would require separate supplemental funding | D10: Risk Register (Doc 10), Category IV
A11: 7 | B11: Year 2 and Year 3 include 3% escalation over Year 1 | C11: Modest inflation adjustment consistent with nonprofit norms | D11: BLS CPI projections, conservative
A12: 8 | B12: Contingency (10%) held in reserve | C12: Board-released, not presumed available for operations | D12: Internal governance decision
A13: 9 | B13: 20% funder cap enforced regardless of category | C13: Prevents capture by any single interest | D13: Methodology Board Charter (Doc 07)
A14: 10 | B14: All figures in 2026 US dollars | C14: No inflation adjustment beyond stated 3% Y-over-Y | D14: Standard nonprofit budget convention
